mtlcc.py
mtldbg.py
mtl/builtins.py
mtl/loader.py
mtl/project.py
mtl/translator.py
mtl/writer.py
mtl/debugging/address.py
mtl/debugging/cli_function.py
mtl/debugging/commands.py
mtl/debugging/common_function.py
mtl/debugging/database.py
mtl/debugging/ipc_code.py
mtl/debugging/ipc_function.py
mtl/debugging/process.py
mtl/debugging/asmbin/breakpoint_100.py
mtl/debugging/asmbin/breakpoint_11a4.py
mtl/debugging/asmbin/breakpoint_11b1.py
mtl/debugging/asmbin/breakpoint_win.py
mtl/debugging/asmbin/passpoint_100.py
mtl/debugging/asmbin/passpoint_11a4.py
mtl/debugging/asmbin/passpoint_11b1.py
mtl/debugging/asmbin/passpoint_win.py
mtl/parser/ini.py
mtl/parser/trigger.py
mtl/stdlib/common1.mtl
mtl/stdlib/libmtl.inc
mtl/types/builtins.py
mtl/types/context.py
mtl/types/debugging.py
mtl/types/ini.py
mtl/types/shared.py
mtl/types/translation.py
mtl/types/trigger.py
mtl/utils/binary.py
mtl/utils/compiler.py
mtl/utils/constant.py
mtl/utils/debug.py
mtl/utils/func.py
mtl_mugen-0.2.2.dist-info/METADATA
mtl_mugen-0.2.2.dist-info/WHEEL
mtl_mugen-0.2.2.dist-info/entry_points.txt
mtl_mugen-0.2.2.dist-info/RECORD
