Metadata-Version: 2.4
Name: mtl-mugen
Version: 0.2.2
Project-URL: Repository, https://github.com/ZiddiaMUGEN/MDK
Project-URL: Documentation, https://github.com/ZiddiaMUGEN/MDK/blob/main/mtlcc/SPEC.md
Project-URL: Changelog, https://github.com/ZiddiaMUGEN/MDK/releases
Requires-Dist: psutil>=6.1.1
Requires-Dist: pyreadline3>=3.5.4
